accuralai_router/__init__.py
accuralai_router/base.py
accuralai_router/config.py
accuralai_router/strategies/__init__.py
accuralai_router/strategies/complexity.py
accuralai_router/strategies/direct.py
accuralai_router/strategies/failover.py
accuralai_router/strategies/rules.py
accuralai_router/strategies/weighted.py
accuralai_router-0.2.1.dist-info/METADATA
accuralai_router-0.2.1.dist-info/WHEEL
accuralai_router-0.2.1.dist-info/entry_points.txt
accuralai_router-0.2.1.dist-info/RECORD
