Metadata-Version: 2.4
Name: accuralai-router
Version: 0.2.1
Summary: Routing strategies for the AccuralAI orchestration pipeline.
Project-URL: homepage, https://accural-ai.web.app/
Project-URL: repository, https://github.com/AccuralAI/accuralai-router
Project-URL: documentation, https://accuralai.readthedocs.io/en/latest/packages/accuralai-router/index.html
Author: AccuralAI Maintainers
License: Apache-2.0
Requires-Python: >=3.10
Requires-Dist: accuralai-core
Requires-Dist: pydantic>=2.5
Provides-Extra: dev
Requires-Dist: pytest; extra == 'dev'
Requires-Dist: pytest-anyio; extra == 'dev'
Requires-Dist: pytest-mock; extra == 'dev'
